{"name":"CP002 Validar excepción de OTP","id":"pruebas-notificaciones;cp002-validar-excepción-de-otp","testSteps":[{"number":1,"description":"Example: {tipoDeEntidad\u003d\"EF\", usuario\u003d\"cenitautorizaut@gmail.com\", clave\u003d\"ColombiaAch.2023*\"}","duration":12414,"startTime":"2024-07-30T10:16:49.644-05:00[America/Bogota]","screenshots":[{"screenshot":"38c39ab8bca5a3d25f8f6f13f0c5d1105a93a519b02ab5bd485e323bd4f1fa98.png","timeStamp":1722352622058}],"result":"SUCCESS","precondition":false,"level":0,"children":[{"number":2,"description":"Given Login Restringido \"EF\" \"cenitautorizaut@gmail.com\" \"ColombiaAch.2023*\"","duration":11842,"startTime":"2024-07-30T10:16:49.645-05:00[America/Bogota]","screenshots":[{"screenshot":"6ca6134ada1c8e40dec69c98893af4b4ce5aa8ac9da58c7731d1bb1d61938978.png","timeStamp":1722352621487}],"result":"SUCCESS","precondition":false,"level":1,"children":[{"number":3,"description":"Abrir web","duration":10325,"startTime":"2024-07-30T10:16:49.659-05:00[America/Bogota]","screenshots":[{"screenshot":"ad58161a0454a06d95b1a7fa3ff32478ce4ae3795e9a2943cbc4dd6f1ccc973e.png","timeStamp":1722352619984}],"result":"SUCCESS","precondition":false,"level":2},{"number":4,"description":"Seleccionar tipo entidad: EF","duration":515,"startTime":"2024-07-30T10:16:59.986-05:00[America/Bogota]","screenshots":[{"screenshot":"ad58161a0454a06d95b1a7fa3ff32478ce4ae3795e9a2943cbc4dd6f1ccc973e.png","timeStamp":1722352619996},{"screenshot":"caf3dc003f414aef3f2ba826174d83415c2616b50dd1fbc697e6d5808b6bc9cf.png","timeStamp":1722352620501}],"result":"SUCCESS","precondition":false,"level":2},{"number":5,"description":"Click boton vamos","duration":357,"startTime":"2024-07-30T10:17:00.502-05:00[America/Bogota]","screenshots":[{"screenshot":"caf3dc003f414aef3f2ba826174d83415c2616b50dd1fbc697e6d5808b6bc9cf.png","timeStamp":1722352620509},{"screenshot":"36ab2de96cedde759711add0c30540c786ad81a630c35b4e8e6c316f6d31511a.png","timeStamp":1722352620859}],"result":"SUCCESS","precondition":false,"level":2},{"number":6,"description":"Escribir usuario y contrasena: cenitautorizaut@gmail.com, ColombiaAch.2023*","duration":618,"startTime":"2024-07-30T10:17:00.860-05:00[America/Bogota]","screenshots":[{"screenshot":"36ab2de96cedde759711add0c30540c786ad81a630c35b4e8e6c316f6d31511a.png","timeStamp":1722352620868},{"screenshot":"6ca6134ada1c8e40dec69c98893af4b4ce5aa8ac9da58c7731d1bb1d61938978.png","timeStamp":1722352621478}],"result":"SUCCESS","precondition":false,"level":2}]},{"number":7,"description":"When Ingreso con un usuarios con restriccion","duration":308,"startTime":"2024-07-30T10:17:01.487-05:00[America/Bogota]","screenshots":[{"screenshot":"6ca6134ada1c8e40dec69c98893af4b4ce5aa8ac9da58c7731d1bb1d61938978.png","timeStamp":1722352621494},{"screenshot":"62d506c1fb5fde5b03b6119bf52d9540adb5836872af2c07735351bbf08faebf.png","timeStamp":1722352621794}],"result":"SUCCESS","precondition":false,"level":1,"children":[{"number":8,"description":"Click ingresar","duration":291,"startTime":"2024-07-30T10:17:01.494-05:00[America/Bogota]","screenshots":[{"screenshot":"6ca6134ada1c8e40dec69c98893af4b4ce5aa8ac9da58c7731d1bb1d61938978.png","timeStamp":1722352621500},{"screenshot":"62d506c1fb5fde5b03b6119bf52d9540adb5836872af2c07735351bbf08faebf.png","timeStamp":1722352621785}],"result":"SUCCESS","precondition":false,"level":2}]},{"number":9,"description":"Then El sistema no permite el ingreso","duration":257,"startTime":"2024-07-30T10:17:01.795-05:00[America/Bogota]","screenshots":[{"screenshot":"62d506c1fb5fde5b03b6119bf52d9540adb5836872af2c07735351bbf08faebf.png","timeStamp":1722352621801},{"screenshot":"38c39ab8bca5a3d25f8f6f13f0c5d1105a93a519b02ab5bd485e323bd4f1fa98.png","timeStamp":1722352622052}],"result":"SUCCESS","precondition":false,"level":1,"children":[{"number":10,"description":"Acceso restringido","duration":239,"startTime":"2024-07-30T10:17:01.804-05:00[America/Bogota]","screenshots":[{"screenshot":"62d506c1fb5fde5b03b6119bf52d9540adb5836872af2c07735351bbf08faebf.png","timeStamp":1722352621809},{"screenshot":"38c39ab8bca5a3d25f8f6f13f0c5d1105a93a519b02ab5bd485e323bd4f1fa98.png","timeStamp":1722352622043}],"result":"SUCCESS","precondition":false,"level":2}]}]}],"userStory":{"id":"pruebas-notificaciones","storyName":"Pruebas Notificaciones","path":"src/test/resources/com.integra.ach.features/RestriccionDeHorarios.feature","type":"feature"},"featureTag":{"name":"Features/Pruebas Notificaciones","type":"feature","displayName":"Features/Pruebas Notificaciones"},"title":"CP002 Validar excepción de OTP","tags":[{"name":"CP002","type":"tag","displayName":"CP002"},{"name":"PruebasNotificaciones","type":"tag","displayName":"PruebasNotificaciones"}],"startTime":"2024-07-30T10:16:49.637-05:00[America/Bogota]","duration":13099,"projectKey":"","isManualTestingUpToDate":false,"dataTable":{"headers":["tipoDeEntidad","usuario","clave"],"rows":[{"values":["\"EF\"","\"cenitautorizaut@gmail.com\"","\"ColombiaAch.2023*\""],"result":"SUCCESS"}],"predefinedRows":true,"scenarioOutline":"Given Login Restringido \u003ctipoDeEntidad\u003e \u003cusuario\u003e \u003cclave\u003e\n\rWhen Ingreso con un usuarios con restriccion\n\rThen El sistema no permite el ingreso\n\r","dataSetDescriptors":[{"startRow":0,"rowCount":0,"name":""}]},"manual":false,"testSource":"Cucumber","result":"SUCCESS","scenarioOutline":"Given Login Restringido \u003ctipoDeEntidad\u003e \u003cusuario\u003e \u003cclave\u003e\r\nWhen Ingreso con un usuarios con restriccion\r\nThen El sistema no permite el ingreso"}